doit_tools/__init__.py
doit_tools/py.typed
doit_tools/tasks.py
doit_tools-0.1.5.dist-info/LICENSE
doit_tools-0.1.5.dist-info/WHEEL
doit_tools-0.1.5.dist-info/METADATA
doit_tools-0.1.5.dist-info/RECORD
