Metadata-Version: 2.1
Name: doit_tools
Version: 0.1.5
Summary: Predefined tasks for doit
Author-email: Ali Ghahraei Figueroa <aligf94@gmail.com>
Classifier: Programming Language :: Python :: 3
Classifier: License :: OSI Approved :: MIT License
Classifier: Operating System :: POSIX :: Linux
Classifier: Operating System :: MacOS
Classifier: Operating System :: Unix
Requires-Dist: doit
Requires-Dist: tomlkit
Project-URL: Home, https://github.com/AliGhahraei/doit-tools
